nr/__init__.py
nr/utils/__init__.py
nr/utils/process/__init__.py
nr/utils/process/root.py
nr.utils.process-0.0.5.dist-info/LICENSE.txt
nr.utils.process-0.0.5.dist-info/METADATA
nr.utils.process-0.0.5.dist-info/WHEEL
nr.utils.process-0.0.5.dist-info/top_level.txt
nr.utils.process-0.0.5.dist-info/zip-safe
nr.utils.process-0.0.5.dist-info/RECORD
