Metadata-Version: 2.1
Name: nr.utils.process
Version: 0.0.5
Summary: Utilities for cross-platform process handling and privilege escalation.
Home-page: https://git.niklasrosenstein.com/NiklasRosenstein/nr
Author: Niklas Rosenstein
Author-email: rosensteinniklas@gmail.com
License: MIT
Platform: UNKNOWN
Requires-Python: >=3.4.0,<4.0.0
